odoo8_addon_pos_remove_pos_category-8.0.0.1.0-py2.7-nspkg.pth
odoo8_addon_pos_remove_pos_category-8.0.0.1.0.dist-info/DESCRIPTION.rst
odoo8_addon_pos_remove_pos_category-8.0.0.1.0.dist-info/METADATA
odoo8_addon_pos_remove_pos_category-8.0.0.1.0.dist-info/RECORD
odoo8_addon_pos_remove_pos_category-8.0.0.1.0.dist-info/WHEEL
odoo8_addon_pos_remove_pos_category-8.0.0.1.0.dist-info/metadata.json
odoo8_addon_pos_remove_pos_category-8.0.0.1.0.dist-info/namespace_packages.txt
odoo8_addon_pos_remove_pos_category-8.0.0.1.0.dist-info/top_level.txt
odoo_addons/pos_remove_pos_category/README.rst
odoo_addons/pos_remove_pos_category/__init__.py
odoo_addons/pos_remove_pos_category/__openerp__.py
odoo_addons/pos_remove_pos_category/module.py
odoo_addons/pos_remove_pos_category/point_of_sale_view.xml
odoo_addons/pos_remove_pos_category/product.py
odoo_addons/pos_remove_pos_category/i18n/ar.po
odoo_addons/pos_remove_pos_category/i18n/bg.po
odoo_addons/pos_remove_pos_category/i18n/bs.po
odoo_addons/pos_remove_pos_category/i18n/ca.po
odoo_addons/pos_remove_pos_category/i18n/cs.po
odoo_addons/pos_remove_pos_category/i18n/da.po
odoo_addons/pos_remove_pos_category/i18n/de.po
odoo_addons/pos_remove_pos_category/i18n/en_GB.po
odoo_addons/pos_remove_pos_category/i18n/es.po
odoo_addons/pos_remove_pos_category/i18n/es_AR.po
odoo_addons/pos_remove_pos_category/i18n/es_CO.po
odoo_addons/pos_remove_pos_category/i18n/es_CR.po
odoo_addons/pos_remove_pos_category/i18n/es_EC.po
odoo_addons/pos_remove_pos_category/i18n/es_ES.po
odoo_addons/pos_remove_pos_category/i18n/es_MX.po
odoo_addons/pos_remove_pos_category/i18n/es_PE.po
odoo_addons/pos_remove_pos_category/i18n/es_VE.po
odoo_addons/pos_remove_pos_category/i18n/eu.po
odoo_addons/pos_remove_pos_category/i18n/fa.po
odoo_addons/pos_remove_pos_category/i18n/fi.po
odoo_addons/pos_remove_pos_category/i18n/fr.po
odoo_addons/pos_remove_pos_category/i18n/fr_CH.po
odoo_addons/pos_remove_pos_category/i18n/he.po
odoo_addons/pos_remove_pos_category/i18n/hr.po
odoo_addons/pos_remove_pos_category/i18n/it.po
odoo_addons/pos_remove_pos_category/i18n/ja.po
odoo_addons/pos_remove_pos_category/i18n/lt.po
odoo_addons/pos_remove_pos_category/i18n/lv.po
odoo_addons/pos_remove_pos_category/i18n/mk.po
odoo_addons/pos_remove_pos_category/i18n/mn.po
odoo_addons/pos_remove_pos_category/i18n/nb.po
odoo_addons/pos_remove_pos_category/i18n/nl.po
odoo_addons/pos_remove_pos_category/i18n/nl_BE.po
