Metadata-Version: 2.0
Name: odoo8-addon-pos-remove-pos-category
Version: 8.0.0.1.0
Summary: POS Remove POS Category
Home-page: https://www.akretion.com
Author: Akretion, Odoo Community Association (OCA)
Author-email: support@odoo-community.org
License: AGPL-3
Platform: UNKNOWN
Classifier: Programming Language :: Python :: 2.7
Classifier: Framework :: Odoo
Classifier: License :: OSI Approved :: GNU Affero General Public License v3
Requires-Dist: odoo (<9.0a,>=8.0a)
